shared_models/__init__.py
shared_models/database/__init__.py
shared_models/database/models/__init__.py
shared_models/database/models/company.py
shared_models/database/models/response.py
shared_models/database/models/user.py
shared_models/database/models/vacancy.py
shared_models/database/utils.py
shared_models/enums/__init__.py
shared_models/enums/content_type.py
shared_models/enums/question_type.py
shared_models/enums/subscription_type.py
shared_models/py.typed
jobs_bot_shared_models-0.1.0.dist-info/METADATA
jobs_bot_shared_models-0.1.0.dist-info/WHEEL
jobs_bot_shared_models-0.1.0.dist-info/RECORD
