Metadata-Version: 2.3
Name: jobs-bot-shared-models
Version: 0.1.0
Summary: Shared models for jobs-bot project
Author: ycalk
Author-email: alosev752@gmail.com
Requires-Python: >=3.13
Classifier: Programming Language :: Python :: 3
Classifier: Programming Language :: Python :: 3.13
Requires-Dist: alembic (>=1.16.5,<2.0.0)
Requires-Dist: asyncpg (>=0.30.0,<0.31.0)
Requires-Dist: pytest-asyncio (>=1.2.0,<2.0.0)
Requires-Dist: python-dotenv (>=1.1.1,<2.0.0)
Requires-Dist: sqlalchemy[asyncio] (>=2.0.43,<3.0.0)
